README.rst
setup.py
DadardWebsiteApi.egg-info/PKG-INFO
DadardWebsiteApi.egg-info/SOURCES.txt
DadardWebsiteApi.egg-info/dependency_links.txt
DadardWebsiteApi.egg-info/requires.txt
DadardWebsiteApi.egg-info/top_level.txt
MainWebsiteApi/__init__.py