Metadata-Version: 1.1
Name: DadardWebsiteApi
Version: 0.25
Summary: This API allows to manage profile account on Dadard Website
Home-page: http://dadard.fr:8010/dadard/MainWebsiteApi.git
Author: Florian Charpentier
Author-email: florian.charpentier@epita.fr
License: WTFPL
Platform: UNKNOWN
Classifier: Environment :: Web Environment
Classifier: Framework :: Flask
Classifier: Intended Audience :: Developers
Classifier: License :: Freeware
Classifier: Operating System :: OS Independent
Classifier: Programming Language :: Python
Classifier: Programming Language :: Python :: 3.6
Classifier: Topic :: Internet :: WWW/HTTP
Classifier: Topic :: Internet :: WWW/HTTP :: Dynamic Content
